minibar/__init__.py
minibar/formatter.py
minibar/widgets.py
minibar-0.5.0.dist-info/DESCRIPTION.rst
minibar-0.5.0.dist-info/METADATA
minibar-0.5.0.dist-info/metadata.json
minibar-0.5.0.dist-info/RECORD
minibar-0.5.0.dist-info/top_level.txt
minibar-0.5.0.dist-info/WHEEL
