Metadata-Version: 2.0
Name: minibar
Version: 0.5.0
Summary: Simple text progress bar library
Home-page: https://github.com/canassa/minibar
Author: Cesar Canassa
Author-email: cesar@canassa.com
License: MIT
Keywords: progressbar progress bar
Platform: UNKNOWN
Classifier: Development Status :: 3 - Alpha
Classifier: Intended Audience :: Developers
Classifier: Intended Audience :: System Administrators
Classifier: Topic :: Software Development :: Libraries
Classifier: Topic :: Software Development :: User Interfaces
Classifier: Topic :: Utilities
Classifier: License :: OSI Approved :: MIT License
Classifier: Programming Language :: Python :: 2.6
Classifier: Programming Language :: Python :: 2.7
Classifier: Programming Language :: Python :: 3.4
